Bani/Bani.py
Bani/__init__.py
Bani/test.py
Bani/core/FAQ.py
Bani/core/__init__.py
Bani/core/defaults.py
Bani/core/exceptions.py
Bani/core/generation.py
Bani/generation/__init__.py
Bani/generation/rajat_work/__init__.py
Bani/generation/rajat_work/qgen/__init__.py
Bani/generation/rajat_work/qgen/encoder/__init__.py
Bani/generation/rajat_work/qgen/encoder/base.py
Bani/generation/rajat_work/qgen/encoder/dummy.py
Bani/generation/rajat_work/qgen/encoder/fasttext.py
Bani/generation/rajat_work/qgen/encoder/glove.py
Bani/generation/rajat_work/qgen/generator/__init__.py
Bani/generation/rajat_work/qgen/generator/base.py
Bani/generation/rajat_work/qgen/generator/eda.py
Bani/generation/rajat_work/qgen/generator/imt.py
Bani/generation/rajat_work/qgen/generator/symsub.py
Bani/generation/rajat_work/qgen/generator/zeroshot.py
Bani/generation/rajat_work/qgen/generator/fpm/__init__.py
Bani/generation/rajat_work/qgen/generator/fpm/fpm.py
Bani/generation/rajat_work/qgen/generator/fpm/matcher.py
Bani/generation/rajat_work/qgen/generator/fpm/pattern.py
Bani/generation/rajat_work/qgen/util/__init__.py
Bani/generation/rajat_work/qgen/util/config.py
Bani/generation/rajat_work/qgen/util/file.py
Bani/generation/rajat_work/qgen/util/nlp.py
Bani/generation/sentAug/__init__.py
Bani/generation/sentAug/sentAug.py
Bani/generation/t5_paraphrase_gen/abbreviation.py
Bani/generation/t5_paraphrase_gen/abbreviation_helper.py
Bani/generation/t5_paraphrase_gen/t5_paraphrase.py
Bani/modelRelated/__init__.py
Bani/modelRelated/batchHardDataset.py
Bani/modelRelated/config.py
Bani/modelRelated/customLosses.py
Bani/modelRelated/lossHandler.py
Bani/modelRelated/softmaxDataset.py
Bani/modelRelated/utils.py
Bani-0.7.2.dist-info/LICENSE
Bani-0.7.2.dist-info/METADATA
Bani-0.7.2.dist-info/WHEEL
Bani-0.7.2.dist-info/top_level.txt
Bani-0.7.2.dist-info/RECORD
