Metadata-Version: 2.1
Name: Bani
Version: 0.7.2
Summary: UNKNOWN
Home-page: https://github.com/captanlevi/FAQ-QnA-matching.git
Author: Rushi Babaria
Author-email: rjlinkin50@gmail.com
License: UNKNOWN
Platform: UNKNOWN
Requires-Python: >=3.6
License-File: LICENSE
Requires-Dist: sentence-transformers (==0.3.8)
Requires-Dist: nltk (==3.5)
Requires-Dist: abbreviations (==0.2.5)
Requires-Dist: pandas
Requires-Dist: numpy
Requires-Dist: regex
Requires-Dist: nlpaug
Requires-Dist: spacy
Requires-Dist: tqdm
